pgcloader/__init__.py
pgcloader/pgcloader.py
pgcloader-1.0.0a1.dist-info/DESCRIPTION.rst
pgcloader-1.0.0a1.dist-info/METADATA
pgcloader-1.0.0a1.dist-info/RECORD
pgcloader-1.0.0a1.dist-info/WHEEL
pgcloader-1.0.0a1.dist-info/metadata.json
pgcloader-1.0.0a1.dist-info/top_level.txt
