Metadata-Version: 2.0
Name: pgcloader
Version: 1.0.0a1
Summary: A sample Python API wrapper for load data from S3 to Cavatica
Home-page: https://github.com/d3b-center/s3-sbg-loader
Author: Yuankun Zhu
Author-email: zhuyuank@gmail.com
License: MIT
Platform: UNKNOWN
Classifier: Development Status :: 3 - Alpha
Classifier: Intended Audience :: Developers
Classifier: Topic :: Software Development :: Build Tools
Classifier: License :: OSI Approved :: MIT License
Classifier: Programming Language :: Python :: 2.7
Requires-Dist: ConfigParser
Requires-Dist: csv
Requires-Dist: json
Requires-Dist: requests
